gramex/__init__.py
gramex/__main__.py
gramex/apps.yaml
gramex/cache.py
gramex/config.py
gramex/data.py
gramex/debug.py
gramex/deploy.yaml
gramex/download.vega.js
gramex/favicon.ico
gramex/gramex.yaml
gramex/gramexfeatures.csv
gramex/gramexsize.csv
gramex/http.py
gramex/install.py
gramex/license.py
gramex/migrate.py
gramex/ml.py
gramex/ml_api.py
gramex/pynode.py
gramex/scale.py
gramex/secrets.py
gramex/servicenow.yaml
gramex/sm_api.py
gramex/topcause.py
gramex/transformers.py
gramex/winservice.py
gramex/apps/__init__.py
gramex/apps/admin/.gitignore
gramex/apps/admin/gramex.yaml
gramex/apps/admin2/admin.css
gramex/apps/admin2/gramex.yaml
gramex/apps/admin2/gramexadmin.py
gramex/apps/admin2/index.html
gramex/apps/admin2/schedule.js
gramex/apps/capture/.snyk
gramex/apps/capture/README.md
gramex/apps/capture/capture.js
gramex/apps/capture/chromecapture.js
gramex/apps/capture/index.html
gramex/apps/capture/package-lock.json
gramex/apps/capture/package.json
gramex/apps/filemanager/README.html
gramex/apps/filemanager/drivehandler-snippet.html
gramex/apps/filemanager/filemanager-snippet.html
gramex/apps/filemanager/filemanager.html
gramex/apps/filemanager/filemanager.js
gramex/apps/filemanager/filemanager.py
gramex/apps/filemanager/gramex.yaml
gramex/apps/filemanager/index.html
gramex/apps/filemanager/navbar.html
gramex/apps/init/default/.eslintrc.yml
gramex/apps/init/default/.gitlab-ci.yml
gramex/apps/init/default/.secrets.yaml
gramex/apps/init/default/.template.gitignore
gramex/apps/init/default/README.template.md
gramex/apps/init/default/gramex.template.yaml
gramex/apps/init/default/index.template.html
gramex/apps/init/default/login.template.html
gramex/apps/init/default/package.template.json
gramex/apps/init/default/style.scss
gramex/apps/init/default/template-navbar.template.html
gramex/apps/init/default/assets/README.template.md
gramex/apps/init/default/js/README.template.md
gramex/apps/init/ide/.gitlab-ci.template.yml
gramex/apps/init/ide/gramex.template.yaml
gramex-1.94.5.dist-info/LICENSE
gramex-1.94.5.dist-info/METADATA
gramex-1.94.5.dist-info/WHEEL
gramex-1.94.5.dist-info/entry_points.txt
gramex-1.94.5.dist-info/top_level.txt
gramex-1.94.5.dist-info/RECORD
